quicksemble/__init__.py
quicksemble/classifier_transformer.py
quicksemble/ensembler.py
quicksemble/utils.py
quicksemble-0.2.8.dist-info/METADATA
quicksemble-0.2.8.dist-info/RECORD
quicksemble-0.2.8.dist-info/WHEEL
quicksemble-0.2.8.dist-info/top_level.txt
