Metadata-Version: 2.1
Name: quicksemble
Version: 0.2.8
Summary: A package to build ensemble for quick experiments.
Home-page: https://github.com/SubigyaPanta/quicksemble
Author: Subigya Jyoti Panta
Author-email: subigya@t2pco.com
License: UNKNOWN
Project-URL: Bug Reports, https://github.com/SubigyaPanta/quicksemble/issues
Project-URL: Source, https://github.com/SubigyaPanta/quicksemble
Platform: UNKNOWN
Classifier: Development Status :: 4 - Beta
Classifier: Topic :: Scientific/Engineering :: Artificial Intelligence
Classifier: Programming Language :: Python :: 3
Classifier: Programming Language :: Python :: 3.6
Classifier: Programming Language :: Python :: 3.7
Classifier: Intended Audience :: Education
Classifier: Intended Audience :: Science/Research
Classifier: Intended Audience :: Information Technology
Classifier: Intended Audience :: Developers
Classifier: License :: OSI Approved :: GNU General Public License v3 (GPLv3)
Classifier: Operating System :: OS Independent
Requires-Dist: numpy
Requires-Dist: scikit-learn
Requires-Dist: xgboost
